AUTHORS.rst
CHANGES.rst
CITATION
CONTRIBUTING.rst
lightkurve/__init__.py
lightkurve/collections.py
lightkurve/config/__init__.py
lightkurve/convenience.py
lightkurve/correctors/__init__.py
lightkurve/correctors/cbvcorrector.py
lightkurve/correctors/corrector.py
lightkurve/correctors/designmatrix.py
lightkurve/correctors/metrics.py
lightkurve/correctors/pldcorrector.py
lightkurve/correctors/regressioncorrector.py
lightkurve/correctors/sffcorrector.py
lightkurve/data/lc-ext0-header.txt
lightkurve/data/lc-ext1-header.txt
lightkurve/data/lc-ext2-header.txt
lightkurve/data/lightkurve.mplstyle
lightkurve/data/short_cadence_month_lookup.csv
lightkurve/data/show_citation_instructions.html
lightkurve/data/tpf-ext0-header.txt
lightkurve/data/tpf-ext1-header.txt
lightkurve/data/tpf-ext2-header.txt
lightkurve/interact.py
lightkurve/interact_bls.py
lightkurve/io/__init__.py
lightkurve/io/cdips.py
lightkurve/io/detect.py
lightkurve/io/eleanor.py
lightkurve/io/everest.py
lightkurve/io/generic.py
lightkurve/io/k2sff.py
lightkurve/io/kepler.py
lightkurve/io/kepseismic.py
lightkurve/io/pathos.py
lightkurve/io/qlp.py
lightkurve/io/read.py
lightkurve/io/tasoc.py
lightkurve/io/tess.py
lightkurve/io/tglc.py
lightkurve/lightcurve.py
lightkurve/lightcurvefile.py
lightkurve/periodogram.py
lightkurve/prf/__init__.py
lightkurve/prf/prfmodel.py
lightkurve/prf/tpfmodel.py
lightkurve/search.py
lightkurve/seismology/__init__.py
lightkurve/seismology/core.py
lightkurve/seismology/deltanu_estimators.py
lightkurve/seismology/numax_estimators.py
lightkurve/seismology/stellar_estimators.py
lightkurve/seismology/utils.py
lightkurve/targetpixelfile.py
lightkurve/time.py
lightkurve/units.py
lightkurve/utils.py
lightkurve/version.py
lightkurve-2.4.1.dist-info/LICENSE
lightkurve-2.4.1.dist-info/METADATA
lightkurve-2.4.1.dist-info/WHEEL
lightkurve-2.4.1.dist-info/RECORD
