Metadata-Version: 2.1
Name: lightkurve
Version: 2.4.1
Summary: A friendly package for Kepler & TESS time series analysis in Python.
Home-page: https://docs.lightkurve.org
License: MIT
Keywords: NASA,Kepler,TESS,Astronomy
Author: Geert Barentsen
Author-email: hello@geert.io
Requires-Python: >=3.8
Classifier: Development Status :: 5 - Production/Stable
Classifier: Intended Audience :: Science/Research
Classifier: License :: OSI Approved :: MIT License
Classifier: Operating System :: OS Independent
Classifier: Programming Language :: Python
Classifier: Programming Language :: Python :: 3
Classifier: Programming Language :: Python :: 3.8
Classifier: Programming Language :: Python :: 3.9
Classifier: Programming Language :: Python :: 3.10
Classifier: Programming Language :: Python :: 3.11
Classifier: Topic :: Scientific/Engineering :: Astronomy
Requires-Dist: astropy (>=5.0)
Requires-Dist: astroquery (>=0.3.10)
Requires-Dist: beautifulsoup4 (>=4.6.0)
Requires-Dist: bokeh (>=2.0.0)
Requires-Dist: fbpca (>=1.0)
Requires-Dist: matplotlib (>=3.1)
Requires-Dist: memoization (>=0.3.1) ; python_version >= "3.8" and python_version < "4.0"
Requires-Dist: numpy (>=1.18)
Requires-Dist: oktopus (>=0.1.2)
Requires-Dist: pandas (>=1.1.4)
Requires-Dist: patsy (>=0.5.0)
Requires-Dist: requests (>=2.22.0)
Requires-Dist: scikit-learn (>=0.24.0)
Requires-Dist: scipy (>=1.7) ; python_version >= "3.8" and python_version < "3.11"
Requires-Dist: tqdm (>=4.25.0)
Requires-Dist: uncertainties (>=3.1.4)
Requires-Dist: urllib3 (>=1.23) ; python_version >= "3.8" and python_version < "4.0"
Project-URL: Bug Tracker, https://github.com/lightkurve/lightkurve/issues
Project-URL: Documentation, https://docs.lightkurve.org
Project-URL: Repository, https://github.com/lightkurve/lightkurve
